{"CHN": {"popularity": 200,  "Country": "China"}, "KHM": {"popularity": 140, "Country": "Cambodia"},
"LAO": {"popularity": 160,  "Country": "Laos"},
"FRA": {"popularity": 200,  "Country": "France"}, "USA": {"popularity": 350,  "Country": "USA"},
"JPN": {"popularity": 400,  "Country": "Japan"},
"SGP": {"popularity": 800, "Country": "Singapore"}, "MYS": {"popularity": 150, "Country": "Malaysia"},
"PHL": {"popularity": 220, "Country": "Philippines"},
"EGY": {"popularity": 100,  "Country": "Egypt"}, "ITA": {"popularity": 300,  "Country": "Italy"},
"IDN": {"popularity": 270,  "Country": "Indonesia"},
"GBR": {"popularity": 200,  "Country": "Great Britain"}, "ARG": {"popularity": 600,  "Country": "Argentina"},
"IND": {"popularity": 400,  "Country": "India"},
"RUS": {"popularity": 100, "Country": "Russia"}, "KOR": {"popularity": 50, "Country": "South Korea"},
"VNM": {"popularity": 250,  "Country": "Viet Nam"}, "AUS": {"popularity": 450, "Country": "Australia"},
"THA": {"popularity": 200,  "Country": "Thailand"}}
